cloudquery/__init__.py
py_cloudquery-0.1.3.dist-info/METADATA
py_cloudquery-0.1.3.dist-info/WHEEL
py_cloudquery-0.1.3.dist-info/top_level.txt
py_cloudquery-0.1.3.dist-info/RECORD
