Metadata-Version: 2.4
Name: py-cloudquery
Version: 0.1.3
Summary: Meta package for cloudquery CLI, selects the right binary for your platform.
Author-email: CloudQuery <info@cloudquery.io>
Requires-Python: >=3.7
Requires-Dist: py-cloudquery-mac-arm64; platform_system == "Darwin" and platform_machine == "arm64"
Requires-Dist: py-cloudquery-mac-amd64; platform_system == "Darwin" and platform_machine == "x86_64"
Requires-Dist: py-cloudquery-linux-arm64; platform_system == "Linux" and platform_machine == "aarch64"
Requires-Dist: py-cloudquery-linux-amd64; platform_system == "Linux" and platform_machine == "x86_64"
Requires-Dist: py-cloudquery-windows-arm64; platform_system == "Windows" and platform_machine == "ARM64"
Requires-Dist: py-cloudquery-windows-amd64; platform_system == "Windows" and platform_machine == "AMD64"
